HiCLift/__init__.py
HiCLift/chainfile.py
HiCLift/io.py
HiCLift/liftover.py
HiCLift/utilities.py
HiCLift/data/juicer_tools_1.11.09_jcuda.0.8.jar
HiCLift-1.0.data/scripts/HiCLift
HiCLift-1.0.dist-info/LICENSE
HiCLift-1.0.dist-info/METADATA
HiCLift-1.0.dist-info/WHEEL
HiCLift-1.0.dist-info/top_level.txt
HiCLift-1.0.dist-info/RECORD
