Metadata-Version: 2.1
Name: HiCLift
Version: 1.0
Summary: Convert genomic coordinates of contact pairs from one assembly to another.
Home-page: https://github.com/XiaoTaoWang/HiCLift
Author: XiaoTao Wang
Author-email: wangxiaotao686@gmail.com
Keywords: liftover pairs Hi-C 4DN
Classifier: Programming Language :: Python :: 3.6
Classifier: License :: OSI Approved :: GNU General Public License v3 or later (GPLv3+)
Classifier: Operating System :: POSIX
Classifier: Development Status :: 3 - Alpha
Classifier: Intended Audience :: Science/Research
Classifier: Topic :: Scientific/Engineering :: Bio-Informatics
License-File: LICENSE
